gitmoji/__init__.py
gitmoji/core.py
gitmoji/exceptions.py
gitmoji/loaders.py
gitmoji/model.py
gitmoji/py.typed
gitmoji/typing.py
gitmoji/assets/gitmojis.json
gitmoji/cli/__init__.py
gitmoji/cli/commands.py
gitmoji/cli/constants.py
gitmoji/cli/helpers.py
python_gitmoji-1.0.1.dist-info/LICENSE
python_gitmoji-1.0.1.dist-info/METADATA
python_gitmoji-1.0.1.dist-info/WHEEL
python_gitmoji-1.0.1.dist-info/entry_points.txt
python_gitmoji-1.0.1.dist-info/top_level.txt
python_gitmoji-1.0.1.dist-info/RECORD
